{
    "boxShadow": "none",
    "mobileBottomRow": 42,
    "widgetName": "Input1",
    "iconSVG": "/static/media/icon.d0ce957b6c4640f8a7418ce846ee200e.svg",
    "displayName": "Input",
    "topRow": 35,
    "searchTags": [
        "form",
        "text input",
        "number",
        "textarea"
    ],
    "bottomRow": 42,
    "parentRowSpace": 10,
    "labelWidth": 5,
    "autoFocus": false,
    "type": "INPUT_WIDGET_V2",
    "hideCard": false,
    "mobileRightColumn": 26,
    "animateLoading": true,
    "parentColumnSpace": 12.578125,
    "resetOnSubmit": true,
    "leftColumn": 6,
    "dynamicBindingPathList": [
        {"key": "accentColor"},
        {"key": "borderRadius"}
    ],
    "labelPosition": "Top",
    "labelStyle": "",
    "inputType": "TEXT",
    "isDisabled": false,
    "key": "jvokklwhyb",
    "labelTextSize": "0.875rem",
    "isRequired": false,
    "isDeprecated": false,
    "rightColumn": 26,
    "dynamicHeight": "FIXED",
    "accentColor": "{{appsmith.theme.colors.primaryColor}}",
    "widgetId": "oy65avtjem",
    "showStepArrows": false,
    "minWidth": 450,
    "isVisible": true,
    "label": "Label",
    "version": 2,
    "parentId": "0",
    "isLoading": false,
    "labelAlignment": "left",
    "renderMode": "CANVAS",
    "mobileTopRow": 35,
    "responsiveBehavior": "fill",
    "borderRadius": "{{appsmith.theme.borderRadius.appBorderRadius}}",
    "mobileLeftColumn": 6,
    "maxDynamicHeight": 9000,
    "iconAlign": "left",
    "defaultText": "",
    "minDynamicHeight": 4
}